pyLivestatus/__init__.py
pyLivestatus/base.py
pyLivestatus/columns.py
pyLivestatus/exceptions.py
pyLivestatus-1.0.4.dist-info/LICENSE
pyLivestatus-1.0.4.dist-info/METADATA
pyLivestatus-1.0.4.dist-info/WHEEL
pyLivestatus-1.0.4.dist-info/top_level.txt
pyLivestatus-1.0.4.dist-info/RECORD
