Metadata-Version: 2.1
Name: pyLivestatus
Version: 1.0.4
Summary: Python library for Livestatus Integration
Home-page: https://github.com/ElmecOSS/pyLivestatus
Author: Luca Depaoli
Author-email: luca.depaoli@elmec.it
License: MIT
Keywords: pyLivestatus,nagios,nagios socket
Platform: any
Classifier: Development Status :: 1 - Planning
Classifier: Environment :: Web Environment
Classifier: Intended Audience :: Developers
Classifier: License :: OSI Approved :: GNU General Public License v3 (GPLv3)
Classifier: Operating System :: OS Independent
Classifier: Programming Language :: Python
Classifier: Topic :: Software Development :: Libraries :: Python Modules
